qlispreg/__init__.py
qlispreg/dicttree.py
qlispreg/expression.py
qlispreg/version.py
qlispreg-0.0.1.dist-info/LICENSE
qlispreg-0.0.1.dist-info/METADATA
qlispreg-0.0.1.dist-info/WHEEL
qlispreg-0.0.1.dist-info/top_level.txt
qlispreg-0.0.1.dist-info/RECORD
